Embedded Micro System Design/HW4/hw4b/hw4b.v
module hw4b(a, b, s, f); 
    input[3:0] a;
    input[3:0] b;
    input[3:0] s;
    output[3:0] f;

reg[3:0] f;
always@(a or b or s)
begin
        case(s)
		    4'b0000:
		        f = ~a;
		    4'b0001:
		        f = ~(a & b);
		    4'b0010:
		        f = ~a | b;
		    4'b0011:
		        f = "0001";
		    4'b0100:
		        f = ~(a | b);
		    4'b0101:
		        f = ~b;
		    4'b0110:
		        f = ~(a ^ b);
		    4'b0111:
		        f = a | ~b;
		    4'b1000:
		        f = ~a & b;
		    4'b1001:
		        f = a ^ b;
		    4'b1010:
		        f = b;
		    4'b1011:
		        f = a | b;
		    4'b1100:
		        f = "0000";
		    4'b1101:
		        f <= a & ~b;
		    4'b1110:
		        f = a & b;
		    4'b1111:
		        f = a;
		endcase
    end
endmodule

Embedded Micro System Design/HW4/hw4b/hw4b.vcd
$comment
Copyright (C) 1991-2010 Altera Corporation
Your use of Altera Corporation's design tools, logic functions 
and other software and tools, and its AMPP partner logic 
functions, and any output files from any of the foregoing 
(including device programming or simulation files), and any 
associated documentation or information are expressly subject 
to the terms and conditions of the Altera Program License 
Subscription Agreement, Altera MegaCore Function License 
Agreement, or other applicable license agreement, including, 
without limitation, that your use is for the sole purpose of 
programming logic devices manufactured by Altera and sold by 
Altera or its authorized distributors.  Please refer to the 
applicable agreement for further details.
$end

$date 
  10/05/2013 21:24:32 
$end
$version 
 QUARTUS_VCD_EXPORT 1.0 
$end
$timescale
  1 ps
$end
$scope module hw4b $end
$var reg 4 ! a[3:0] $end
$var reg 4 " b[3:0] $end
$var reg 4 # f[3:0] $end
$var reg 4 $ s[3:0] $end
$upscope $end
$enddefinitions $end
#0
$dumpvars
b11 !
b1010 "
b1100 #
b0 $
$end
#1000
b1101 #
b1 $
#2000
b1110 #
b10 $
#3000
b1 #
b11 $
#4000
b100 #
b100 $
#5000
b101 #
b101 $
#6000
b110 #
b110 $
#7000
b111 #
b111 $
#8000
b1000 #
b1000 $
#9000
b1001 #
b1001 $
#10000
b1010 #
b1010 $
#11000
b1011 #
b1011 $
#12000
b0 #
b1100 $
#13000
b1 #
b1101 $
#14000
b10 #
b1110 $
#15000
b11 #
b1111 $
#16000
b1100 #
b0 $
#17000
b1101 #
b1 $
#18000
b1110 #
b10 $
#19000
b1 #
b11 $
#20000
b100 #
b100 $
#21000
b101 #
b101 $
#22000
b110 #
b110 $
#23000
b111 #
b111 $
#24000
b1000 #
b1000 $
#25000
b1001 #
b1001 $
#26000
b1010 #
b1010 $
#27000
b1011 #
b1011 $
#28000
b0 #
b1100 $
#29000
b1 #
b1101 $
#30000
b10 #
b1110 $
#31000
b11 #
b1111 $
#32000
b1100 #
b0 $
#33000
b1101 #
b1 $
#34000
b1110 #
b10 $
#35000
b1 #
b11 $
#36000
b100 #
b100 $
#37000
b101 #
b101 $
#38000
b110 #
b110 $
#39000
b111 #
b111 $
#40000
b1000 #
b1000 $
#41000
b1001 #
b1001 $
#42000
b1010 #
b1010 $
#43000
b1011 #
b1011 $
#44000
b0 #
b1100 $
#45000
b1 #
b1101 $
#46000
b10 #
b1110 $
#47000
b11 #
b1111 $
#48000
b1100 #
b0 $
#49000
b1101 #
b1 $
#50000
b1110 #
b10 $
#51000
b1 #
b11 $
#52000
b100 #
b100 $
#53000
b101 #
b101 $
#54000
b110 #
b110 $
#55000
b111 #
b111 $
#56000
b1000 #
b1000 $
#57000
b1001 #
b1001 $
#58000
b1010 #
b1010 $
#59000
b1011 #
b1011 $
#60000
b0 #
b1100 $
#61000
b1 #
b1101 $
#62000
b10 #
b1110 $
#63000
b11 #
b1111 $
#64000
b1100 #
b0 $
#65000
b1101 #
b1 $
#66000
b1110 #
b10 $
#67000
b1 #
b11 $
#68000
b100 #
b100 $
#69000
b101 #
b101 $
#70000
b110 #
b110 $
#71000
b111 #
b111 $
#72000
b1000 #
b1000 $
#73000
b1001 #
b1001 $
#74000
b1010 #
b1010 $
#75000
b1011 #
b1011 $
#76000
b0 #
b1100 $
#77000
b1 #
b1101 $
#78000
b10 #
b1110 $
#79000
b11 #
b1111 $
#80000
b1100 #
b0 $
#81000
b1101 #
b1 $
#82000
b1110 #
b10 $
#83000
b1 #
b11 $
#84000
b100 #
b100 $
#85000
b101 #
b101 $
#86000
b110 #
b110 $
#87000
b111 #
b111 $
#88000
b1000 #
b1000 $
#89000
b1001 #
b1001 $
#90000
b1010 #
b1010 $
#91000
b1011 #
b1011 $
#92000
b0 #
b1100 $
#93000
b1 #
b1101 $
#94000
b10 #
b1110 $
#95000
b11 #
b1111 $
#96000
b1100 #
b0 $
#97000
b1101 #
b1 $
#98000
b1110 #
b10 $
#99000
b1 #
b11 $
#100000
b100 #
b100 $
#101000
b101 #
b101 $
#102000
b110 #
b110 $
#103000
b111 #
b111 $
#104000
b1000 #
b1000 $
#105000
b1001 #
b1001 $
#106000
b1010 #
b1010 $
#107000
b1011 #
b1011 $
#108000
b0 #
b1100 $
#109000
b1 #
b1101 $
#110000
b10 #
b1110 $
#111000
b11 #
b1111 $
#112000
b1100 #
b0 $
#113000
b1101 #
b1 $
#114000
b1110 #
b10 $
#115000
b1 #
b11 $
#116000
b100 #
b100 $
#117000
b101 #
b101 $
#118000
b110 #
b110 $
#119000
b111 #
b111 $
#120000
b1000 #
b1000 $
#121000
b1001 #
b1001 $
#122000
b1010 #
b1010 $
#123000
b1011 #
b1011 $
#124000
b0 #
b1100 $
#125000
b1 #
b1101 $
#126000
b10 #
b1110 $
#127000
b11 #
b1111 $
#128000
b1100 #
b0 $
#129000
b1101 #
b1 $
#130000
b1110 #
b10 $
#131000
b1 #
b11 $
#132000
b100 #
b100 $
#133000
b101 #
b101 $
#134000
b110 #
b110 $
#135000
b111 #
b111 $
#136000
b1000 #
b1000 $
#137000
b1001 #
b1001 $
#138000
b1010 #
b1010 $
#139000
b1011 #
b1011 $
#140000
b0 #
b1100 $
#141000
b1 #
b1101 $
#142000
b10 #
b1110 $
#143000
b11 #
b1111 $
#144000
b1100 #
b0 $
#145000
b1101 #
b1 $
#146000
b1110 #
b10 $
#147000
b1 #
b11 $
#148000
b100 #
b100 $
#149000
b101 #
b101 $
#150000
b110 #
b110 $
#151000
b111 #
b111 $
#152000
b1000 #
b1000 $
#153000
b1001 #
b1001 $
#154000
b1010 #
b1010 $
#155000
b1011 #
b1011 $
#156000
b0 #
b1100 $
#157000
b1 #
b1101 $
#158000
b10 #
b1110 $
#159000
b11 #
b1111 $
#160000
b1100 #
b0 $
#161000
b1101 #
b1 $
#162000
b1110 #
b10 $
#163000
b1 #
b11 $
#164000
b100 #
b100 $
#165000
b101 #
b101 $
#166000
b110 #
b110 $
#167000
b111 #
b111 $
#168000
b1000 #
b1000 $
#169000
b1001 #
b1001 $
#170000
b1010 #
b1010 $
#171000
b1011 #
b1011 $
#172000
b0 #
b1100 $
#173000
b1 #
b1101 $
#174000
b10 #
b1110 $
#175000
b11 #
b1111 $
#176000
b1100 #
b0 $
#177000
b1101 #
b1 $
#178000
b1110 #
b10 $
#179000
b1 #
b11 $
#180000
b100 #
b100 $
#181000
b101 #
b101 $
#182000
b110 #
b110 $
#183000
b111 #
b111 $
#184000
b1000 #
b1000 $
#185000
b1001 #
b1001 $
#186000
b1010 #
b1010 $
#187000
b1011 #
b1011 $
#188000
b0 #
b1100 $
#189000
b1 #
b1101 $
#190000
b10 #
b1110 $
#191000
b11 #
b1111 $
#192000
b1100 #
b0 $
#193000
b1101 #
b1 $
#194000
b1110 #
b10 $
#195000
b1 #
b11 $
#196000
b100 #
b100 $
#197000
b101 #
b101 $
#198000
b110 #
b110 $
#199000
b111 #
b111 $
#200000
b1000 #
b1000 $
#201000
b1001 #
b1001 $
#202000
b1010 #
b1010 $
#203000
b1011 #
b1011 $
#204000
b0 #
b1100 $
#205000
b1 #
b1101 $
#206000
b10 #
b1110 $
#207000
b11 #
b1111 $
#208000
b1100 #
b0 $
#209000
b1101 #
b1 $
#210000
b1110 #
b10 $
#211000
b1 #
b11 $
#212000
b100 #
b100 $
#213000
b101 #
b101 $
#214000
b110 #
b110 $
#215000
b111 #
b111 $
#216000
b1000 #
b1000 $
#217000
b1001 #
b1001 $
#218000
b1010 #
b1010 $
#219000
b1011 #
b1011 $
#220000
b0 #
b1100 $
#221000
b1 #
b1101 $
#222000
b10 #
b1110 $
#223000
b11 #
b1111 $
#224000
b1100 #
b0 $
#225000
b1101 #
b1 $
#226000
b1110 #
b10 $
#227000
b1 #
b11 $
#228000
b100 #
b100 $
#229000
b101 #
b101 $
#230000
b110 #
b110 $
#231000
b111 #
b111 $
#232000
b1000 #
b1000 $
#233000
b1001 #
b1001 $
#234000
b1010 #
b1010 $
#235000
b1011 #
b1011 $
#236000
b0 #
b1100 $
#237000
b1 #
b1101 $
#238000
b10 #
b1110 $
#239000
b11 #
b1111 $
#240000
b1100 #
b0 $
#241000
b1101 #
b1 $
#242000
b1110 #
b10 $
#243000
b1 #
b11 $
#244000
b100 #
b100 $
#245000
b101 #
b101 $
#246000
b110 #
b110 $
#247000
b111 #
b111 $
#248000
b1000 #
b1000 $
#249000
b1001 #
b1001 $
#250000
b1010 #
b1010 $
#251000
b1011 #
b1011 $
#252000
b0 #
b1100 $
#253000
b1 #
b1101 $
#254000
b10 #
b1110 $
#255000
b11 #
b1111 $
#256000
b1100 #
b0 $
#257000
b1101 #
b1 $
#258000
b1110 #
b10 $
#259000
b1 #
b11 $
#260000
b100 #
b100 $
#261000
b101 #
b101 $
#262000
b110 #
b110 $
#263000
b111 #
b111 $
#264000
b1000 #
b1000 $
#265000
b1001 #
b1001 $
#266000
b1010 #
b1010 $
#267000
b1011 #
b1011 $
#268000
b0 #
b1100 $
#269000
b1 #
b1101 $
#270000
b10 #
b1110 $
#271000
b11 #
b1111 $
#272000
b1100 #
b0 $
#273000
b1101 #
b1 $
#274000
b1110 #
b10 $
#275000
b1 #
b11 $
#276000
b100 #
b100 $
#277000
b101 #
b101 $
#278000
b110 #
b110 $
#279000
b111 #
b111 $
#280000
b1000 #
b1000 $
#281000
b1001 #
b1001 $
#282000
b1010 #
b1010 $
#283000
b1011 #
b1011 $
#284000
b0 #
b1100 $
#285000
b1 #
b1101 $
#286000
b10 #
b1110 $
#287000
b11 #
b1111 $
#288000
b1100 #
b0 $
#289000
b1101 #
b1 $
#290000
b1110 #
b10 $
#291000
b1 #
b11 $
#292000
b100 #
b100 $
#293000
b101 #
b101 $
#294000
b110 #
b110 $
#295000
b111 #
b111 $
#296000
b1000 #
b1000 $
#297000
b1001 #
b1001 $
#298000
b1010 #
b1010 $
#299000
b1011 #
b1011 $
#300000
b0 #
b1100 $
#301000
b1 #
b1101 $
#302000
b10 #
b1110 $
#303000
b11 #
b1111 $
#304000
b1100 #
b0 $
#305000
b1101 #
b1 $
#306000
b1110 #
b10 $
#307000
b1 #
b11 $
#308000
b100 #
b100 $
#309000
b101 #
b101 $
#310000
b110 #
b110 $
#311000
b111 #
b111 $
#312000
b1000 #
b1000 $
#313000
b1001 #
b1001 $
#314000
b1010 #
b1010 $
#315000
b1011 #
b1011 $
#316000
b0 #
b1100 $
#317000
b1 #
b1101 $
#318000
b10 #
b1110 $
#319000
b11 #
b1111 $
#320000
b1100 #
b0 $
#321000
b1101 #
b1 $
#322000
b1110 #
b10 $
#323000
b1 #
b11 $
#324000
b100 #
b100 $
#325000
b101 #
b101 $
#326000
b110 #
b110 $
#327000
b111 #
b111 $
#328000
b1000 #
b1000 $
#329000
b1001 #
b1001 $
#330000
b1010 #
b1010 $
#331000
b1011 #
b1011 $
#332000
b0 #
b1100 $
#333000
b1 #
b1101 $
#334000
b10 #
b1110 $
#335000
b11 #
b1111 $
#336000
b1100 #
b0 $
#337000
b1101 #
b1 $
#338000
b1110 #
b10 $
#339000
b1 #
b11 $
#340000
b100 #
b100 $
#341000
b101 #
b101 $
#342000
b110 #
b110 $
#343000
b111 #
b111 $
#344000
b1000 #
b1000 $
#345000
b1001 #
b1001 $
#346000
b1010 #
b1010 $
#347000
b1011 #
b1011 $
#348000
b0 #
b1100 $
#349000
b1 #
b1101 $
#350000
b10 #
b1110 $
#351000
b11 #
b1111 $
#352000
b1100 #
b0 $
#353000
b1101 #
b1 $
#354000
b1110 #
b10 $
#355000
b1 #
b11 $
#356000
b100 #
b100 $
#357000
b101 #
b101 $
#358000
b110 #
b110 $
#359000
b111 #
b111 $
#360000
b1000 #
b1000 $
#361000
b1001 #
b1001 $
#362000
b1010 #
b1010 $
#363000
b1011 #
b1011 $
#364000
b0 #
b1100 $
#365000
b1 #
b1101 $
#366000
b10 #
b1110 $
#367000
b11 #
b1111 $
#368000
b1100 #
b0 $
#369000
b1101 #
b1 $
#370000
b1110 #
b10 $
#371000
b1 #
b11 $
#372000
b100 #
b100 $
#373000
b101 #
b101 $
#374000
b110 #
b110 $
#375000
b111 #
b111 $
#376000
b1000 #
b1000 $
#377000
b1001 #
b1001 $
#378000
b1010 #
b1010 $
#379000
b1011 #
b1011 $
#380000
b0 #
b1100 $
#381000
b1 #
b1101 $
#382000
b10 #
b1110 $
#383000
b11 #
b1111 $
#384000
b1100 #
b0 $
#385000
b1101 #
b1 $
#386000
b1110 #
b10 $
#387000
b1 #
b11 $
#388000
b100 #
b100 $
#389000
b101 #
b101 $
#390000
b110 #
b110 $
#391000
b111 #
b111 $
#392000
b1000 #
b1000 $
#393000
b1001 #
b1001 $
#394000
b1010 #
b1010 $
#395000
b1011 #
b1011 $
#396000
b0 #
b1100 $
#397000
b1 #
b1101 $
#398000
b10 #
b1110 $
#399000
b11 #
b1111 $
#400000
b1100 #
b0 $
#401000
b1101 #
b1 $
#402000
b1110 #
b10 $
#403000
b1 #
b11 $
#404000
b100 #
b100 $
#405000
b101 #
b101 $
#406000
b110 #
b110 $
#407000
b111 #
b111 $
#408000
b1000 #
b1000 $
#409000
b1001 #
b1001 $
#410000
b1010 #
b1010 $
#411000
b1011 #
b1011 $
#412000
b0 #
b1100 $
#413000
b1 #
b1101 $
#414000
b10 #
b1110 $
#415000
b11 #
b1111 $
#416000
b1100 #
b0 $
#417000
b1101 #
b1 $
#418000
b1110 #
b10 $
#419000
b1 #
b11 $
#420000
b100 #
b100 $
#421000
b101 #
b101 $
#422000
b110 #
b110 $
#423000
b111 #
b111 $
#424000
b1000 #
b1000 $
#425000
b1001 #
b1001 $
#426000
b1010 #
b1010 $
#427000
b1011 #
b1011 $
#428000
b0 #
b1100 $
#429000
b1 #
b1101 $
#430000
b10 #
b1110 $
#431000
b11 #
b1111 $
#432000
b1100 #
b0 $
#433000
b1101 #
b1 $
#434000
b1110 #
b10 $
#435000
b1 #
b11 $
#436000
b100 #
b100 $
#437000
b101 #
b101 $
#438000
b110 #
b110 $
#439000
b111 #
b111 $
#440000
b1000 #
b1000 $
#441000
b1001 #
b1001 $
#442000
b1010 #
b1010 $
#443000
b1011 #
b1011 $
#444000
b0 #
b1100 $
#445000
b1 #
b1101 $
#446000
b10 #
b1110 $
#447000
b11 #
b1111 $
#448000
b1100 #
b0 $
#449000
b1101 #
b1 $
#450000
b1110 #
b10 $
#451000
b1 #
b11 $
#452000
b100 #
b100 $
#453000
b101 #
b101 $
#454000
b110 #
b110 $
#455000
b111 #
b111 $
#456000
b1000 #
b1000 $
#457000
b1001 #
b1001 $
#458000
b1010 #
b1010 $
#459000
b1011 #
b1011 $
#460000
b0 #
b1100 $
#461000
b1 #
b1101 $
#462000
b10 #
b1110 $
#463000
b11 #
b1111 $
#464000
b1100 #
b0 $
#465000
b1101 #
b1 $
#466000
b1110 #
b10 $
#467000
b1 #
b11 $
#468000
b100 #
b100 $
#469000
b101 #
b101 $
#470000
b110 #
b110 $
#471000
b111 #
b111 $
#472000
b1000 #
b1000 $
#473000
b1001 #
b1001 $
#474000
b1010 #
b1010 $
#475000
b1011 #
b1011 $
#476000
b0 #
b1100 $
#477000
b1 #
b1101 $
#478000
b10 #
b1110 $
#479000
b11 #
b1111 $
#480000
b1100 #
b0 $
#481000
b1101 #
b1 $
#482000
b1110 #
b10 $
#483000
b1 #
b11 $
#484000
b100 #
b100 $
#485000
b101 #
b101 $
#486000
b110 #
b110 $
#487000
b111 #
b111 $
#488000
b1000 #
b1000 $
#489000
b1001 #
b1001 $
#490000
b1010 #
b1010 $
#491000
b1011 #
b1011 $
#492000
b0 #
b1100 $
#493000
b1 #
b1101 $
#494000
b10 #
b1110 $
#495000
b11 #
b1111 $
#496000
b1100 #
b0 $
#497000
b1101 #
b1 $
#498000
b1110 #
b10 $
#499000
b1 #
b11 $
#500000
b100 #
b100 $
#501000
b101 #
b101 $
#502000
b110 #
b110 $
#503000
b111 #
b111 $
#504000
b1000 #
b1000 $
#505000
b1001 #
b1001 $
#506000
b1010 #
b1010 $
#507000
b1011 #
b1011 $
#508000
b0 #
b1100 $
#509000
b1 #
b1101 $
#510000
b10 #
b1110 $
#511000
b11 #
b1111 $
#512000
b1100 #
b0 $
#513000
b1101 #
b1 $
#514000
b1110 #
b10 $
#515000
b1 #
b11 $
#516000
b100 #
b100 $
#517000
b101 #
b101 $
#518000
b110 #
b110 $
#519000
b111 #
b111 $
#520000
b1000 #
b1000 $
#521000
b1001 #
b1001 $
#522000
b1010 #
b1010 $
#523000
b1011 #
b1011 $
#524000
b0 #
b1100 $
#525000
b1 #
b1101 $
#526000
b10 #
b1110 $
#527000
b11 #
b1111 $
#528000
b1100 #
b0 $
#529000
b1101 #
b1 $
#530000
b1110 #
b10 $
#531000
b1 #
b11 $
#532000
b100 #
b100 $
#533000
b101 #
b101 $
#534000
b110 #
b110 $
#535000
b111 #
b111 $
#536000
b1000 #
b1000 $
#537000
b1001 #
b1001 $
#538000
b1010 #
b1010 $
#539000
b1011 #
b1011 $
#540000
b0 #
b1100 $
#541000
b1 #
b1101 $
#542000
b10 #
b1110 $
#543000
b11 #
b1111 $
#544000
b1100 #
b0 $
#545000
b1101 #
b1 $
#546000
b1110 #
b10 $
#547000
b1 #
b11 $
#548000
b100 #
b100 $
#549000
b101 #
b101 $
#550000
b110 #
b110 $
#551000
b111 #
b111 $
#552000
b1000 #
b1000 $
#553000
b1001 #
b1001 $
#554000
b1010 #
b1010 $
#555000
b1011 #
b1011 $
#556000
b0 #
b1100 $
#557000
b1 #
b1101 $
#558000
b10 #
b1110 $
#559000
b11 #
b1111 $
#560000
b1100 #
b0 $
#561000
b1101 #
b1 $
#562000
b1110 #
b10 $
#563000
b1 #
b11 $
#564000
b100 #
b100 $
#565000
b101 #
b101 $
#566000
b110 #
b110 $
#567000
b111 #
b111 $
#568000
b1000 #
b1000 $
#569000
b1001 #
b1001 $
#570000
b1010 #
b1010 $
#571000
b1011 #
b1011 $
#572000
b0 #
b1100 $
#573000
b1 #
b1101 $
#574000
b10 #
b1110 $
#575000
b11 #
b1111 $
#576000
b1100 #
b0 $
#577000
b1101 #
b1 $
#578000
b1110 #
b10 $
#579000
b1 #
b11 $
#580000
b100 #
b100 $
#581000
b101 #
b101 $
#582000
b110 #
b110 $
#583000
b111 #
b111 $
#584000
b1000 #
b1000 $
#585000
b1001 #
b1001 $
#586000
b1010 #
b1010 $
#587000
b1011 #
b1011 $
#588000
b0 #
b1100 $
#589000
b1 #
b1101 $
#590000
b10 #
b1110 $
#591000
b11 #
b1111 $
#592000
b1100 #
b0 $
#593000
b1101 #
b1 $
#594000
b1110 #
b10 $
#595000
b1 #
b11 $
#596000
b100 #
b100 $
#597000
b101 #
b101 $
#598000
b110 #
b110 $
#599000
b111 #
b111 $
#600000
b1000 #
b1000 $
#601000
b1001 #
b1001 $
#602000
b1010 #
b1010 $
#603000
b1011 #
b1011 $
#604000
b0 #
b1100 $
#605000
b1 #
b1101 $
#606000
b10 #
b1110 $
#607000
b11 #
b1111 $
#608000
b1100 #
b0 $
#609000
b1101 #
b1 $
#610000
b1110 #
b10 $
#611000
b1 #
b11 $
#612000
b100 #
b100 $
#613000
b101 #
b101 $
#614000
b110 #
b110 $
#615000
b111 #
b111 $
#616000
b1000 #
b1000 $
#617000
b1001 #
b1001 $
#618000
b1010 #
b1010 $
#619000
b1011 #
b1011 $
#620000
b0 #
b1100 $
#621000
b1 #
b1101 $
#622000
b10 #
b1110 $
#623000
b11 #
b1111 $
#624000
b1100 #
b0 $
#625000
b1101 #
b1 $
#626000
b1110 #
b10 $
#627000
b1 #
b11 $
#628000
b100 #
b100 $
#629000
b101 #
b101 $
#630000
b110 #
b110 $
#631000
b111 #
b111 $
#632000
b1000 #
b1000 $
#633000
b1001 #
b1001 $
#634000
b1010 #
b1010 $
#635000
b1011 #
b1011 $
#636000
b0 #
b1100 $
#637000
b1 #
b1101 $
#638000
b10 #
b1110 $
#639000
b11 #
b1111 $
#640000
b1100 #
b0 $
#641000
b1101 #
b1 $
#642000
b1110 #
b10 $
#643000
b1 #
b11 $
#644000
b100 #
b100 $
#645000
b101 #
b101 $
#646000
b110 #
b110 $
#647000
b111 #
b111 $
#648000
b1000 #
b1000 $
#649000
b1001 #
b1001 $
#650000
b1010 #
b1010 $
#651000
b1011 #
b1011 $
#652000
b0 #
b1100 $
#653000
b1 #
b1101 $
#654000
b10 #
b1110 $
#655000
b11 #
b1111 $
#656000
b1100 #
b0 $
#657000
b1101 #
b1 $
#658000
b1110 #
b10 $
#659000
b1 #
b11 $
#660000
b100 #
b100 $
#661000
b101 #
b101 $
#662000
b110 #
b110 $
#663000
b111 #
b111 $
#664000
b1000 #
b1000 $
#665000
b1001 #
b1001 $
#666000
b1010 #
b1010 $
#667000
b1011 #
b1011 $
#668000
b0 #
b1100 $
#669000
b1 #
b1101 $
#670000
b10 #
b1110 $
#671000
b11 #
b1111 $
#672000
b1100 #
b0 $
#673000
b1101 #
b1 $
#674000
b1110 #
b10 $
#675000
b1 #
b11 $
#676000
b100 #
b100 $
#677000
b101 #
b101 $
#678000
b110 #
b110 $
#679000
b111 #
b111 $
#680000
b1000 #
b1000 $
#681000
b1001 #
b1001 $
#682000
b1010 #
b1010 $
#683000
b1011 #
b1011 $
#684000
b0 #
b1100 $
#685000
b1 #
b1101 $
#686000
b10 #
b1110 $
#687000
b11 #
b1111 $
#688000
b1100 #
b0 $
#689000
b1101 #
b1 $
#690000
b1110 #
b10 $
#691000
b1 #
b11 $
#692000
b100 #
b100 $
#693000
b101 #
b101 $
#694000
b110 #
b110 $
#695000
b111 #
b111 $
#696000
b1000 #
b1000 $
#697000
b1001 #
b1001 $
#698000
b1010 #
b1010 $
#699000
b1011 #
b1011 $
#700000
b0 #
b1100 $
#701000
b1 #
b1101 $
#702000
b10 #
b1110 $
#703000
b11 #
b1111 $
#704000
b1100 #
b0 $
#705000
b1101 #
b1 $
#706000
b1110 #
b10 $
#707000
b1 #
b11 $
#708000
b100 #
b100 $
#709000
b101 #
b101 $
#710000
b110 #
b110 $
#711000
b111 #
b111 $
#712000
b1000 #
b1000 $
#713000
b1001 #
b1001 $
#714000
b1010 #
b1010 $
#715000
b1011 #
b1011 $
#716000
b0 #
b1100 $
#717000
b1 #
b1101 $
#718000
b10 #
b1110 $
#719000
b11 #
b1111 $
#720000
b1100 #
b0 $
#721000
b1101 #
b1 $
#722000
b1110 #
b10 $
#723000
b1 #
b11 $
#724000
b100 #
b100 $
#725000
b101 #
b101 $
#726000
b110 #
b110 $
#727000
b111 #
b111 $
#728000
b1000 #
b1000 $
#729000
b1001 #
b1001 $
#730000
b1010 #
b1010 $
#731000
b1011 #
b1011 $
#732000
b0 #
b1100 $
#733000
b1 #
b1101 $
#734000
b10 #
b1110 $
#735000
b11 #
b1111 $
#736000
b1100 #
b0 $
#737000
b1101 #
b1 $
#738000
b1110 #
b10 $
#739000
b1 #
b11 $
#740000
b100 #
b100 $
#741000
b101 #
b101 $
#742000
b110 #
b110 $
#743000
b111 #
b111 $
#744000
b1000 #
b1000 $
#745000
b1001 #
b1001 $
#746000
b1010 #
b1010 $
#747000
b1011 #
b1011 $
#748000
b0 #
b1100 $
#749000
b1 #
b1101 $
#750000
b10 #
b1110 $
#751000
b11 #
b1111 $
#752000
b1100 #
b0 $
#753000
b1101 #
b1 $
#754000
b1110 #
b10 $
#755000
b1 #
b11 $
#756000
b100 #
b100 $
#757000
b101 #
b101 $
#758000
b110 #
b110 $
#759000
b111 #
b111 $
#760000
b1000 #
b1000 $
#761000
b1001 #
b1001 $
#762000
b1010 #
b1010 $
#763000
b1011 #
b1011 $
#764000
b0 #
b1100 $
#765000
b1 #
b1101 $
#766000
b10 #
b1110 $
#767000
b11 #
b1111 $
#768000
b1100 #
b0 $
#769000
b1101 #
b1 $
#770000
b1110 #
b10 $
#771000
b1 #
b11 $
#772000
b100 #
b100 $
#773000
b101 #
b101 $
#774000
b110 #
b110 $
#775000
b111 #
b111 $
#776000
b1000 #
b1000 $
#777000
b1001 #
b1001 $
#778000
b1010 #
b1010 $
#779000
b1011 #
b1011 $
#780000
b0 #
b1100 $
#781000
b1 #
b1101 $
#782000
b10 #
b1110 $
#783000
b11 #
b1111 $
#784000
b1100 #
b0 $
#785000
b1101 #
b1 $
#786000
b1110 #
b10 $
#787000
b1 #
b11 $
#788000
b100 #
b100 $
#789000
b101 #
b101 $
#790000
b110 #
b110 $
#791000
b111 #
b111 $
#792000
b1000 #
b1000 $
#793000
b1001 #
b1001 $
#794000
b1010 #
b1010 $
#795000
b1011 #
b1011 $
#796000
b0 #
b1100 $
#797000
b1 #
b1101 $
#798000
b10 #
b1110 $
#799000
b11 #
b1111 $
#800000
b1100 #
b0 $
#801000
b1101 #
b1 $
#802000
b1110 #
b10 $
#803000
b1 #
b11 $
#804000
b100 #
b100 $
#805000
b101 #
b101 $
#806000
b110 #
b110 $
#807000
b111 #
b111 $
#808000
b1000 #
b1000 $
#809000
b1001 #
b1001 $
#810000
b1010 #
b1010 $
#811000
b1011 #
b1011 $
#812000
b0 #
b1100 $
#813000
b1 #
b1101 $
#814000
b10 #
b1110 $
#815000
b11 #
b1111 $
#816000
b1100 #
b0 $
#817000
b1101 #
b1 $
#818000
b1110 #
b10 $
#819000
b1 #
b11 $
#820000
b100 #
b100 $
#821000
b101 #
b101 $
#822000
b110 #
b110 $
#823000
b111 #
b111 $
#824000
b1000 #
b1000 $
#825000
b1001 #
b1001 $
#826000
b1010 #
b1010 $
#827000
b1011 #
b1011 $
#828000
b0 #
b1100 $
#829000
b1 #
b1101 $
#830000
b10 #
b1110 $
#831000
b11 #
b1111 $
#832000
b1100 #
b0 $
#833000
b1101 #
b1 $
#834000
b1110 #
b10 $
#835000
b1 #
b11 $
#836000
b100 #
b100 $
#837000
b101 #
b101 $
#838000
b110 #
b110 $
#839000
b111 #
b111 $
#840000
b1000 #
b1000 $
#841000
b1001 #
b1001 $
#842000
b1010 #
b1010 $
#843000
b1011 #
b1011 $
#844000
b0 #
b1100 $
#845000
b1 #
b1101 $
#846000
b10 #
b1110 $
#847000
b11 #
b1111 $
#848000
b1100 #
b0 $
#849000
b1101 #
b1 $
#850000
b1110 #
b10 $
#851000
b1 #
b11 $
#852000
b100 #
b100 $
#853000
b101 #
b101 $
#854000
b110 #
b110 $
#855000
b111 #
b111 $
#856000
b1000 #
b1000 $
#857000
b1001 #
b1001 $
#858000
b1010 #
b1010 $
#859000
b1011 #
b1011 $
#860000
b0 #
b1100 $
#861000
b1 #
b1101 $
#862000
b10 #
b1110 $
#863000
b11 #
b1111 $
#864000
b1100 #
b0 $
#865000
b1101 #
b1 $
#866000
b1110 #
b10 $
#867000
b1 #
b11 $
#868000
b100 #
b100 $
#869000
b101 #
b101 $
#870000
b110 #
b110 $
#871000
b111 #
b111 $
#872000
b1000 #
b1000 $
#873000
b1001 #
b1001 $
#874000
b1010 #
b1010 $
#875000
b1011 #
b1011 $
#876000
b0 #
b1100 $
#877000
b1 #
b1101 $
#878000
b10 #
b1110 $
#879000
b11 #
b1111 $
#880000
b1100 #
b0 $
#881000
b1101 #
b1 $
#882000
b1110 #
b10 $
#883000
b1 #
b11 $
#884000
b100 #
b100 $
#885000
b101 #
b101 $
#886000
b110 #
b110 $
#887000
b111 #
b111 $
#888000
b1000 #
b1000 $
#889000
b1001 #
b1001 $
#890000
b1010 #
b1010 $
#891000
b1011 #
b1011 $
#892000
b0 #
b1100 $
#893000
b1 #
b1101 $
#894000
b10 #
b1110 $
#895000
b11 #
b1111 $
#896000
b1100 #
b0 $
#897000
b1101 #
b1 $
#898000
b1110 #
b10 $
#899000
b1 #
b11 $
#900000
b100 #
b100 $
#901000
b101 #
b101 $
#902000
b110 #
b110 $
#903000
b111 #
b111 $
#904000
b1000 #
b1000 $
#905000
b1001 #
b1001 $
#906000
b1010 #
b1010 $
#907000
b1011 #
b1011 $
#908000
b0 #
b1100 $
#909000
b1 #
b1101 $
#910000
b10 #
b1110 $
#911000
b11 #
b1111 $
#912000
b1100 #
b0 $
#913000
b1101 #
b1 $
#914000
b1110 #
b10 $
#915000
b1 #
b11 $
#916000
b100 #
b100 $
#917000
b101 #
b101 $
#918000
b110 #
b110 $
#919000
b111 #
b111 $
#920000
b1000 #
b1000 $
#921000
b1001 #
b1001 $
#922000
b1010 #
b1010 $
#923000
b1011 #
b1011 $
#924000
b0 #
b1100 $
#925000
b1 #
b1101 $
#926000
b10 #
b1110 $
#927000
b11 #
b1111 $
#928000
b1100 #
b0 $
#929000
b1101 #
b1 $
#930000
b1110 #
b10 $
#931000
b1 #
b11 $
#932000
b100 #
b100 $
#933000
b101 #
b101 $
#934000
b110 #
b110 $
#935000
b111 #
b111 $
#936000
b1000 #
b1000 $
#937000
b1001 #
b1001 $
#938000
b1010 #
b1010 $
#939000
b1011 #
b1011 $
#940000
b0 #
b1100 $
#941000
b1 #
b1101 $
#942000
b10 #
b1110 $
#943000
b11 #
b1111 $
