Embedded Micro System Design/HW3/hw3b/hw3b.vhd
library ieee;
use ieee.std_logic_1164.all;

entity hw3b is
	port 
	(
		a	   : in std_logic_vector (3 downto 0);
		b	   : in std_logic_vector (3 downto 0);
		s      : in std_logic_vector (3 downto 0);
		
		f       : out std_logic_vector (3 downto 0)
	);

end entity;

architecture logic of hw3b is
begin

process(a,b,s)
    
    begin
        case s is
		    when "0000" =>
		        f <= NOT a;
		    when "0001" =>
		        f <= NOT (a and b);
		    when "0010" =>
		        f <= NOT a or b;
		    when "0011" =>
		        f <= "0001";
		    when "0100" =>
		        f <= NOT (a or b);
		    when "0101" =>
		        f <= NOT b;
		    when "0110" =>
		        f <= NOT (a xor b);
		    when "0111" =>
		        f <= a or NOT b;
		    when "1000" =>
		        f <= not a and b;
		    when "1001" =>
		        f <= a xor b;
		    when "1010" =>
		        f <= b;
		    when "1011" =>
		        f <= a or b;
		    when "1100" =>
		        f <= "0000";
		    when "1101" =>
		        f <= a and not b;
		    when "1110" =>
		        f <= a and b;
		    when "1111" =>
		        f <= a;
		end case;
    end process;

end logic;

Embedded Micro System Design/HW3/hw3b/hw3b.vcd
$comment
Copyright (C) 1991-2010 Altera Corporation
Your use of Altera Corporation's design tools, logic functions 
and other software and tools, and its AMPP partner logic 
functions, and any output files from any of the foregoing 
(including device programming or simulation files), and any 
associated documentation or information are expressly subject 
to the terms and conditions of the Altera Program License 
Subscription Agreement, Altera MegaCore Function License 
Agreement, or other applicable license agreement, including, 
without limitation, that your use is for the sole purpose of 
programming logic devices manufactured by Altera and sold by 
Altera or its authorized distributors.  Please refer to the 
applicable agreement for further details.
$end

$date 
  09/25/2013 10:18:11 
$end
$version 
 QUARTUS_VCD_EXPORT 1.0 
$end
$timescale
  1 ps
$end
$scope module hw3b $end
$var reg 4 ! s[3:0] $end
$var reg 4 " a[3:0] $end
$var reg 4 # b[3:0] $end
$var reg 4 $ f[3:0] $end
$upscope $end
$enddefinitions $end
#0
$dumpvars
b1 !
b11 "
b1010 #
b1101 $
$end
#5000
b11 !
b1 $
#10000
b1100 !
b0 $
#15000
b100 !
b100 $
#20000
b1000 !
b1000 $
#25000
b1001 !
b1001 $
#30000
b1010 !
b1010 $
#35000
b100 !
b100 $
#40000
b1 !
b1101 $
#45000
b0 !
b1100 $
#55000
b1101 !
b1 $
#60000
b1011 !
b1011 $
#65000
b100 !
b100 $
#70000
b10 !
b1110 $
#75000
b1 !
b1101 $
#80000
b10 !
b1110 $
#85000
b1000 !
b1000 $
#90000
b1101 !
b1 $
#95000
b1110 !
b10 $
#100000
b1000 !
b1000 $
#105000
b10 !
b1110 $
#110000
b1011 !
b1011 $
#115000
b1010 !
b1010 $
#120000
b101 !
b101 $
#125000
b1111 !
b11 $
#130000
b11 !
b1 $
#135000
b1111 !
b11 $
#140000
b1011 !
b1011 $
#145000
b0 !
b1100 $
#150000
b1010 !
b1010 $
#155000
b1 !
b1101 $
#160000
b110 !
b110 $
#165000
b1100 !
b0 $
#170000
b1010 !
b1010 $
#175000
b1110 !
b10 $
#180000
b110 !
b110 $
#185000
b11 !
b1 $
#190000
b110 !
b110 $
#195000
b1101 !
b1 $
#200000
b1010 !
b1010 $
#205000
b1 !
b1101 $
#210000
b101 !
b101 $
#215000
b1110 !
b10 $
#220000
b1010 !
b1010 $
#225000
b111 !
b111 $
#230000
b1101 !
b1 $
#235000
b0 !
b1100 $
#240000
b1100 !
b0 $
#245000
b0 !
b1100 $
#250000
b100 !
b100 $
#255000
b1011 !
b1011 $
#265000
b1101 !
b1 $
#270000
b11 !
#275000
b100 !
b100 $
#280000
b1010 !
b1010 $
#285000
b110 !
b110 $
#290000
b100 !
b100 $
#300000
b111 !
b111 $
#310000
b1101 !
b1 $
#315000
b1001 !
b1001 $
#320000
b10 !
b1110 $
#325000
b1 !
b1101 $
#330000
b111 !
b111 $
#335000
b1111 !
b11 $
#340000
b1001 !
b1001 $
#345000
b1011 !
b1011 $
#350000
b111 !
b111 $
#355000
b1000 !
b1000 $
#360000
b100 !
b100 $
#365000
b10 !
b1110 $
#370000
b110 !
b110 $
#375000
b101 !
b101 $
#380000
b1000 !
b1000 $
#390000
b1100 !
b0 $
#395000
b1110 !
b10 $
#405000
b1011 !
b1011 $
#410000
b0 !
b1100 $
#415000
b1101 !
b1 $
#420000
b1 !
b1101 $
#425000
b110 !
b110 $
#430000
b0 !
b1100 $
#435000
b11 !
b1 $
#440000
b1 !
b1101 $
#445000
b1110 !
b10 $
#450000
b1010 !
b1010 $
#455000
b101 !
b101 $
#460000
b1001 !
b1001 $
#465000
b111 !
b111 $
#470000
b1101 !
b1 $
#480000
b1110 !
b10 $
#485000
b1111 !
b11 $
#490000
b1001 !
b1001 $
#495000
b1101 !
b1 $
#500000
b110 !
b110 $
#505000
b100 !
b100 $
#510000
b1101 !
b1 $
#515000
b1 !
b1101 $
#520000
b1101 !
b1 $
#525000
b1000 !
b1000 $
#530000
b1011 !
b1011 $
#535000
b100 !
b100 $
#540000
b1 !
b1101 $
#545000
b111 !
b111 $
#550000
b1000 !
b1000 $
#555000
b111 !
b111 $
#560000
b1001 !
b1001 $
#565000
b1100 !
b0 $
#575000
b1010 !
b1010 $
#580000
b1101 !
b1 $
#585000
b100 !
b100 $
#590000
b1000 !
b1000 $
#595000
b1 !
b1101 $
#600000
b100 !
b100 $
#605000
b10 !
b1110 $
#615000
b1000 !
b1000 $
#620000
b10 !
b1110 $
#625000
b1100 !
b0 $
#635000
b1001 !
b1001 $
#640000
b1110 !
b10 $
#645000
b1101 !
b1 $
#650000
b1011 !
b1011 $
#655000
b1111 !
b11 $
#665000
b11 !
b1 $
#675000
b10 !
b1110 $
#680000
b110 !
b110 $
#685000
b100 !
b100 $
#690000
b1111 !
b11 $
#700000
b1 !
b1101 $
#705000
b111 !
b111 $
#710000
b100 !
b100 $
#715000
b1101 !
b1 $
#720000
b1011 !
b1011 $
#730000
b110 !
b110 $
#735000
b1111 !
b11 $
#745000
b111 !
b111 $
#750000
b1101 !
b1 $
#755000
b100 !
b100 $
#760000
b1100 !
b0 $
#765000
b0 !
b1100 $
#775000
b11 !
b1 $
#780000
b1 !
b1101 $
#785000
b111 !
b111 $
#790000
b11 !
b1 $
#795000
b1110 !
b10 $
#800000
b111 !
b111 $
#805000
b1100 !
b0 $
#810000
b1010 !
b1010 $
#815000
b1111 !
b11 $
#820000
b110 !
b110 $
#825000
b1011 !
b1011 $
#830000
b10 !
b1110 $
#835000
b1011 !
b1011 $
#840000
b1001 !
b1001 $
#845000
b1 !
b1101 $
#850000
b1101 !
b1 $
#855000
b1010 !
b1010 $
#860000
b1100 !
b0 $
#865000
b1101 !
b1 $
#870000
b1111 !
b11 $
#875000
b1110 !
b10 $
#885000
b1011 !
b1011 $
#890000
b0 !
b1100 $
#895000
b1000 !
b1000 $
#900000
b11 !
b1 $
#905000
b1110 !
b10 $
#910000
b110 !
b110 $
#920000
b1010 !
b1010 $
#925000
b1001 !
b1001 $
#930000
b1011 !
b1011 $
#935000
b1010 !
b1010 $
#940000
b110 !
b110 $
#945000
b10 !
b1110 $
#950000
b1001 !
b1001 $
#955000
b1011 !
b1011 $
#960000
b0 !
b1100 $
#965000
b1 !
b1101 $
#970000
b0 !
b1100 $
#975000
b1101 !
b1 $
#980000
b111 !
b111 $
#985000
b10 !
b1110 $
#990000
b1101 !
b1 $
#995000
b1011 !
b1011 $
